pyEDAA/IPXACT/Catalog.py
pyEDAA/IPXACT/Component.py
pyEDAA/IPXACT/Design.py
pyEDAA/IPXACT/DesignConfiguration.py
pyEDAA/IPXACT/GeneratorChain.py
pyEDAA/IPXACT/__init__.py
pyEDAA/IPXACT/py.typed
pyEDAA/IPXACT/Schema/LICENSE.md
pyEDAA/IPXACT/Schema/NOTICE.md
pyEDAA/IPXACT/Schema/README.md
pyEDAA/IPXACT/Schema/__init__.py
pyEDAA/IPXACT/Schema/ieee-1685-2009/README.md
pyEDAA/IPXACT/Schema/ieee-1685-2009/abstractionDefinition.xsd
pyEDAA/IPXACT/Schema/ieee-1685-2009/abstractor.xsd
pyEDAA/IPXACT/Schema/ieee-1685-2009/autoConfigure.xsd
pyEDAA/IPXACT/Schema/ieee-1685-2009/busDefinition.xsd
pyEDAA/IPXACT/Schema/ieee-1685-2009/busInterface.xsd
pyEDAA/IPXACT/Schema/ieee-1685-2009/commonStructures.xsd
pyEDAA/IPXACT/Schema/ieee-1685-2009/component.xsd
pyEDAA/IPXACT/Schema/ieee-1685-2009/configurable.xsd
pyEDAA/IPXACT/Schema/ieee-1685-2009/constraints.xsd
pyEDAA/IPXACT/Schema/ieee-1685-2009/design.xsd
pyEDAA/IPXACT/Schema/ieee-1685-2009/designConfig.xsd
pyEDAA/IPXACT/Schema/ieee-1685-2009/file.xsd
pyEDAA/IPXACT/Schema/ieee-1685-2009/fileType.xsd
pyEDAA/IPXACT/Schema/ieee-1685-2009/generator.xsd
pyEDAA/IPXACT/Schema/ieee-1685-2009/identifier.xsd
pyEDAA/IPXACT/Schema/ieee-1685-2009/index.xsd
pyEDAA/IPXACT/Schema/ieee-1685-2009/memoryMap.xsd
pyEDAA/IPXACT/Schema/ieee-1685-2009/model.xsd
pyEDAA/IPXACT/Schema/ieee-1685-2009/port.xsd
pyEDAA/IPXACT/Schema/ieee-1685-2009/signalDrivers.xsd
pyEDAA/IPXACT/Schema/ieee-1685-2009/simpleTypes.xsd
pyEDAA/IPXACT/Schema/ieee-1685-2009/subInstances.xsd
pyEDAA/IPXACT/Schema/ieee-1685-2014/README.md
pyEDAA/IPXACT/Schema/ieee-1685-2014/abstractionDefinition.xsd
pyEDAA/IPXACT/Schema/ieee-1685-2014/abstractor.xsd
pyEDAA/IPXACT/Schema/ieee-1685-2014/autoConfigure.xsd
pyEDAA/IPXACT/Schema/ieee-1685-2014/busDefinition.xsd
pyEDAA/IPXACT/Schema/ieee-1685-2014/busInterface.xsd
pyEDAA/IPXACT/Schema/ieee-1685-2014/catalog.xsd
pyEDAA/IPXACT/Schema/ieee-1685-2014/commonStructures.xsd
pyEDAA/IPXACT/Schema/ieee-1685-2014/component.xsd
pyedaa_ipxact-0.6.5.dist-info/licenses/LICENSE.md
pyedaa_ipxact-0.6.5.dist-info/METADATA
pyedaa_ipxact-0.6.5.dist-info/WHEEL
pyedaa_ipxact-0.6.5.dist-info/top_level.txt
pyedaa_ipxact-0.6.5.dist-info/RECORD
