Metadata-Version: 2.4
Name: pyEDAA.IPXACT
Version: 0.6.5
Summary: A Document-Object-Model (DOM) for IP-XACT files.
Home-page: https://GitHub.com/edaa-org/pyEDAA.IPXACT
Author: Patrick Lehmann
Author-email: Paebbels@gmail.com
License: Apache-2.0
Project-URL: Documentation, https://edaa-org.GitHub.io/pyEDAA.IPXACT
Project-URL: Source Code, https://GitHub.com/edaa-org/pyEDAA.IPXACT
Project-URL: Issue Tracker, https://GitHub.com/edaa-org/pyEDAA.IPXACT/issues
Classifier: Operating System :: OS Independent
Classifier: Intended Audience :: Developers
Classifier: Topic :: Utilities
Classifier: Topic :: Scientific/Engineering :: Electronic Design Automation (EDA)
Classifier: License :: OSI Approved :: Apache Software License
Classifier: Programming Language :: Python :: 3 :: Only
Classifier: Programming Language :: Python :: 3.11
Classifier: Programming Language :: Python :: 3.12
Classifier: Programming Language :: Python :: 3.13
Classifier: Programming Language :: Python :: 3.14
Classifier: Development Status :: 3 - Alpha
Requires-Python: >=3.11
License-File: LICENSE.md
Requires-Dist: lxml<7.0,>=5.4
Requires-Dist: pyTooling~=8.11
Provides-Extra: doc
Requires-Dist: lxml<7.0,>=5.4; extra == "doc"
Requires-Dist: sphinx~=9.1; extra == "doc"
Requires-Dist: docutils_stubs~=0.0.22; extra == "doc"
Requires-Dist: autoapi>=2.0.1; extra == "doc"
Requires-Dist: sphinx_autodoc_typehints~=3.6; extra == "doc"
Requires-Dist: sphinx_reports~=0.10.0; extra == "doc"
Requires-Dist: sphinx_rtd_theme~=3.1; extra == "doc"
Requires-Dist: sphinx-copybutton>=0.5.0; extra == "doc"
Requires-Dist: sphinxcontrib-mermaid~=2.0; extra == "doc"
Requires-Dist: pyTooling~=8.11; extra == "doc"
Requires-Dist: sphinx_design~=0.7.0; extra == "doc"
Provides-Extra: test
Requires-Dist: lxml<7.0,>=5.4; extra == "test"
Requires-Dist: mypy[reports]~=1.19; extra == "test"
Requires-Dist: xmlschema>=2.3.1; extra == "test"
Requires-Dist: pytest-cov~=7.0; extra == "test"
Requires-Dist: pytest~=9.0; extra == "test"
Requires-Dist: typing_extensions~=4.15; extra == "test"
Requires-Dist: pyTooling~=8.11; extra == "test"
Requires-Dist: Coverage~=7.13; extra == "test"
Provides-Extra: all
Requires-Dist: lxml<7.0,>=5.4; extra == "all"
Requires-Dist: sphinx~=9.1; extra == "all"
Requires-Dist: autoapi>=2.0.1; extra == "all"
Requires-Dist: docutils_stubs~=0.0.22; extra == "all"
Requires-Dist: sphinx_autodoc_typehints~=3.6; extra == "all"
Requires-Dist: sphinx_reports~=0.10.0; extra == "all"
Requires-Dist: sphinx_rtd_theme~=3.1; extra == "all"
Requires-Dist: sphinx-copybutton>=0.5.0; extra == "all"
Requires-Dist: mypy[reports]~=1.19; extra == "all"
Requires-Dist: xmlschema>=2.3.1; extra == "all"
Requires-Dist: sphinxcontrib-mermaid~=2.0; extra == "all"
Requires-Dist: pytest-cov~=7.0; extra == "all"
Requires-Dist: pytest~=9.0; extra == "all"
Requires-Dist: pyTooling~=8.11; extra == "all"
Requires-Dist: sphinx_design~=0.7.0; extra == "all"
Requires-Dist: typing_extensions~=4.15; extra == "all"
Requires-Dist: Coverage~=7.13; extra == "all"
Dynamic: author
Dynamic: author-email
Dynamic: classifier
Dynamic: description
Dynamic: description-content-type
Dynamic: home-page
Dynamic: license
Dynamic: license-file
Dynamic: project-url
Dynamic: provides-extra
Dynamic: requires-dist
Dynamic: requires-python
Dynamic: summary
